aiml/__init__.py
aiml/programs.py
aiml_dsce-1.0.0.dist-info/LICENSE
aiml_dsce-1.0.0.dist-info/METADATA
aiml_dsce-1.0.0.dist-info/WHEEL
aiml_dsce-1.0.0.dist-info/top_level.txt
aiml_dsce-1.0.0.dist-info/RECORD
